fw_gear_fast_surfer/__init__.py
fw_gear_fast_surfer/parser.py
fw_gear_fast_surfer-1.0.6.dist-info/LICENSE
fw_gear_fast_surfer-1.0.6.dist-info/METADATA
fw_gear_fast_surfer-1.0.6.dist-info/WHEEL
fw_gear_fast_surfer-1.0.6.dist-info/RECORD
