Metadata-Version: 2.1
Name: fw-gear-fast-surfer
Version: 1.0.6
Summary: Wrapper for Fast Surfer
Home-page: https://gitlab.com/flywheel-io/flywheel-apps/templates/skeleton
License: MIT
Keywords: Flywheel,Gears
Author: Flywheel
Author-email: support@flywheel.io
Requires-Python: >=3.10,<4.0
Classifier: License :: OSI Approved :: MIT License
Classifier: Programming Language :: Python :: 3
Classifier: Programming Language :: Python :: 3.10
Classifier: Programming Language :: Python :: 3.11
Classifier: Programming Language :: Python :: 3.12
Classifier: Topic :: Scientific/Engineering
Requires-Dist: flywheel-gear-toolkit (>=0.6.18,<0.7.0)
Project-URL: Repository, https://gitlab.com/flywheel-io/flywheel-apps/templates/skeleton
